sugarplot/__init__.py
sugarplot/conftest.py
sugarplot/examples/examples.py
sugarplot/source/fitters.py
sugarplot/source/normalization.py
sugarplot/source/plotters.py
sugarplot/source/prettify.py
sugarplot/test/conftest.py
sugarplot/test/test_fitters.py
sugarplot/test/test_normalization.py
sugarplot/test/test_plotters.py
sugarplot/test/testing.py
sugarplot-0.1.34.dist-info/LICENSE.txt
sugarplot-0.1.34.dist-info/METADATA
sugarplot-0.1.34.dist-info/WHEEL
sugarplot-0.1.34.dist-info/top_level.txt
sugarplot-0.1.34.dist-info/RECORD
